dexp_api/__init__.py
dexp_api/__main__.py
dexp_api-0.1.0.dist-info/WHEEL
dexp_api-0.1.0.dist-info/METADATA
dexp_api-0.1.0.dist-info/RECORD
